<?xml version="1.0" encoding="UTF-8"?>
<!-- edited with XMLSpy v2019 rel. 3 sp1 (http://www.altova.com) by HaihangRen (AMEC) -->
<AMECDataTypes FormatVersion="1">
	<DataType>
		<Name>BIT</Name>
		<BitSize>1</BitSize>
	</DataType>
	<DataType>
		<Name>DINT</Name>
		<BitSize>64</BitSize>
	</DataType>
	<DataType>
		<Name>DUINT</Name>
		<BitSize>64</BitSize>
	</DataType>
  <DataType>
    <Name>UDINT</Name>
    <BitSize>64</BitSize>
  </DataType>
	<DataType>
		<Name>INT</Name>
		<BitSize>32</BitSize>
	</DataType>
	<DataType>
		<Name>UINT</Name>
		<BitSize>32</BitSize>
	</DataType>
	<DataType>
		<Name>SHORT</Name>
		<BitSize>16</BitSize>
	</DataType>
	<DataType>
		<Name>USHORT</Name>
		<BitSize>16</BitSize>
	</DataType>
	<DataType>
		<Name>SBYTE</Name>
		<BitSize>8</BitSize>
	</DataType>
	<DataType>
		<Name>BYTE</Name>
		<BitSize>8</BitSize>
	</DataType>
	<DataType>
		<Name>FLOAT</Name>
		<BitSize>32</BitSize>
	</DataType>
	<DataType>
		<Name>DOUBLE</Name>
		<BitSize>64</BitSize>
	</DataType>
	<DataType>
		<Name>FINGERPRINT</Name>
		<BitSize>128</BitSize>
		<SubItem>
			<Name>BYTE</Name>
			<ByteOffset>0</ByteOffset>
			<Comment>Byte0</Comment>
		</SubItem>
		<SubItem>
			<Name>BYTE</Name>
			<ByteOffset>1</ByteOffset>
			<Comment>Byte1</Comment>
		</SubItem>
		<SubItem>
			<Name>BYTE</Name>
			<ByteOffset>2</ByteOffset>
			<Comment>Byte2</Comment>
		</SubItem>
		<SubItem>
			<Name>BYTE</Name>
			<ByteOffset>3</ByteOffset>
			<Comment>Byte3</Comment>
		</SubItem>
		<SubItem>
			<Name>BYTE</Name>
			<ByteOffset>4</ByteOffset>
			<Comment>Byte4</Comment>
		</SubItem>
		<SubItem>
			<Name>BYTE</Name>
			<ByteOffset>5</ByteOffset>
			<Comment>Byte5</Comment>
		</SubItem>
		<SubItem>
			<Name>BYTE</Name>
			<ByteOffset>6</ByteOffset>
			<Comment>Byte6</Comment>
		</SubItem>
		<SubItem>
			<Name>BYTE</Name>
			<ByteOffset>7</ByteOffset>
			<Comment>Byte7</Comment>
		</SubItem>
		<SubItem>
			<Name>BYTE</Name>
			<ByteOffset>8</ByteOffset>
			<Comment>Byte8</Comment>
		</SubItem>
		<SubItem>
			<Name>BYTE</Name>
			<ByteOffset>9</ByteOffset>
			<Comment>Byte9</Comment>
		</SubItem>
		<SubItem>
			<Name>BYTE</Name>
			<ByteOffset>10</ByteOffset>
			<Comment>Byte10</Comment>
		</SubItem>
		<SubItem>
			<Name>BYTE</Name>
			<ByteOffset>11</ByteOffset>
			<Comment>Byte11</Comment>
		</SubItem>
		<SubItem>
			<Name>BYTE</Name>
			<ByteOffset>12</ByteOffset>
			<Comment>Byte12</Comment>
		</SubItem>
		<SubItem>
			<Name>BYTE</Name>
			<ByteOffset>13</ByteOffset>
			<Comment>Byte13</Comment>
		</SubItem>
		<SubItem>
			<Name>BYTE</Name>
			<ByteOffset>14</ByteOffset>
			<Comment>Byte14</Comment>
		</SubItem>
		<SubItem>
			<Name>BYTE</Name>
			<ByteOffset>15</ByteOffset>
			<Comment>Byte15</Comment>
		</SubItem>
	</DataType>
	<DataType>
		<Name>DEVICENET_MFC_DEFAULT_TX</Name>
		<BitSize>40</BitSize>
		<SubItem>
			<Name>BYTE</Name>
			<ByteOffset>0</ByteOffset>
			<Comment>ExceptionStatus</Comment>
		</SubItem>
		<SubItem>
			<Name>FLOAT</Name>
			<ByteOffset>1</ByteOffset>
			<Comment>Flow(sccm)</Comment>
		</SubItem>
	</DataType>
	<DataType>
		<Name>DEVICENET_MFC_DEFAULT_RX</Name>
		<BitSize>32</BitSize>
		<SubItem>
			<Name>FLOAT</Name>
			<ByteOffset>0</ByteOffset>
			<Comment>FlowSetpoint(sccm)</Comment>
		</SubItem>
	</DataType>
	<DataType>
		<Name>DEVICENET_PC_DEFAULT_TX</Name>
		<BitSize>72</BitSize>
		<SubItem>
			<Name>BYTE</Name>
			<ByteOffset>0</ByteOffset>
			<Comment>ExceptionStatus</Comment>
		</SubItem>
		<SubItem>
			<Name>FLOAT</Name>
			<ByteOffset>1</ByteOffset>
			<Comment>Pressure(torr)</Comment>
		</SubItem>
		<SubItem>
			<Name>FLOAT</Name>
			<ByteOffset>5</ByteOffset>
			<Comment>Flow(sccm)</Comment>
		</SubItem>
	</DataType>
	<DataType>
		<Name>DEVICENET_PC_DEFAULT_RX</Name>
		<BitSize>48</BitSize>
		<SubItem>
			<Name>FLOAT</Name>
			<ByteOffset>0</ByteOffset>
			<Comment>PressureSetpoint(torr)</Comment>
		</SubItem>
		<SubItem>
			<Name>USHORT</Name>
			<ByteOffset>4</ByteOffset>
			<Comment>Instance</Comment>
		</SubItem>
	</DataType>
	<DataType>
		<Name>DEVICE_DIAGNOSTIC_INFO</Name>
		<BitSize>200</BitSize>
		<SubItem>
			<Name>BYTE</Name>
			<ByteOffset>0</ByteOffset>
			<Comment>HandShake</Comment>
		</SubItem>
		<SubItem>
			<Name>FINGERPRINT</Name>
			<ByteOffset>1</ByteOffset>
			<Comment>Fingerprint</Comment>
		</SubItem>
		<SubItem>
			<Name>UINT</Name>
			<ByteOffset>17</ByteOffset>
			<Comment>Status</Comment>
		</SubItem>
		<SubItem>
			<Name>UINT</Name>
			<ByteOffset>21</ByteOffset>
			<Comment>ProcessStep</Comment>
		</SubItem>
	</DataType>
	<DataType>
		<Name>HOST_CONTROL_BLOCK</Name>
		<BitSize>72</BitSize>
		<SubItem>
			<Name>BYTE</Name>
			<ByteOffset>0</ByteOffset>
			<Comment>HandShake</Comment>
		</SubItem>
		<SubItem>
			<Name>UINT</Name>
			<ByteOffset>1</ByteOffset>
			<Comment>ControlCommand</Comment>
		</SubItem>
		<SubItem>
			<Name>UINT</Name>
			<ByteOffset>5</ByteOffset>
			<Comment>ControlParameter</Comment>
		</SubItem>
	</DataType>
</AMECDataTypes>
